fine_calculator/__init__.py
fine_calculator/calculator.py
fine_calculator/finer.py
fine_calc-1.0.0.dist-info/METADATA
fine_calc-1.0.0.dist-info/WHEEL
fine_calc-1.0.0.dist-info/top_level.txt
fine_calc-1.0.0.dist-info/RECORD
